LICENSE
MANIFEST.in
README.md
setup.py
django_advanced_pdf/__init__.py
django_advanced_pdf/admin.py
django_advanced_pdf/apps.py
django_advanced_pdf/models.py
django_advanced_pdf/tasks.py
django_advanced_pdf/tests.py
django_advanced_pdf/urls.py
django_advanced_pdf.egg-info/PKG-INFO
django_advanced_pdf.egg-info/SOURCES.txt
django_advanced_pdf.egg-info/dependency_links.txt
django_advanced_pdf.egg-info/requires.txt
django_advanced_pdf.egg-info/top_level.txt
django_advanced_pdf/_trial_temp/_trial_marker
django_advanced_pdf/_trial_temp/test.log
django_advanced_pdf/engine/__init__.py
django_advanced_pdf/engine/png_images.py
django_advanced_pdf/engine/report_xml.py
django_advanced_pdf/engine/utils.py
django_advanced_pdf/engine/_svglib/svglib.py
django_advanced_pdf/engine/enhanced_paragraph/__init__.py
django_advanced_pdf/engine/enhanced_paragraph/enhanced_paragraph.py
django_advanced_pdf/engine/enhanced_paragraph/parser.py
django_advanced_pdf/engine/enhanced_paragraph/style.py
django_advanced_pdf/engine/enhanced_table/__init__.py
django_advanced_pdf/engine/enhanced_table/data.py
django_advanced_pdf/engine/enhanced_table/data_paragraph.py
django_advanced_pdf/engine/enhanced_table/enhanced_tables.py
django_advanced_pdf/engine/svg_tools/__init__.py
django_advanced_pdf/engine/svg_tools/svg_ruler.py
django_advanced_pdf/engine/svg_tools/svg_scaled_renderer.py
django_advanced_pdf/engine/svg_tools/svg_scaler.py
django_advanced_pdf/migrations/0001_initial.py
django_advanced_pdf/migrations/__init__.py
django_advanced_pdf/pagers/__init__.py
django_advanced_pdf/pagers/base.py
django_advanced_pdf/pagers/border.py
django_advanced_pdf/test_data/errors/basic.png
django_advanced_pdf/test_data/errors/change_header.png
django_advanced_pdf/test_data/errors/estimate.png
django_advanced_pdf/test_data/errors/hidden.png
django_advanced_pdf/test_data/held/abs2/1.png
django_advanced_pdf/test_data/held/abs2/2.png
django_advanced_pdf/test_data/held/abs2/page_count.txt
django_advanced_pdf/test_data/held/abs3/1.png
django_advanced_pdf/test_data/held/abs3/page_count.txt
django_advanced_pdf/test_data/held/background_colour/1.png
django_advanced_pdf/test_data/held/background_colour/page_count.txt
