Metadata-Version: 2.4
Name: django-advanced-pdf
Version: 0.2.21
Summary: Django app that helps one create pdf
Home-page: https://github.com/django-advance-utils/django-advanced-pdf
Author: Thomas Turner
Classifier: Programming Language :: Python :: 3
Classifier: License :: OSI Approved :: MIT License
Classifier: Operating System :: OS Independent
Requires-Python: >=3.6
License-File: LICENSE
Requires-Dist: svglib>=1.5.1
Requires-Dist: reportlab>=4.2.5
Requires-Dist: lxml>=5.3.0
Dynamic: author
Dynamic: classifier
Dynamic: description
Dynamic: description-content-type
Dynamic: home-page
Dynamic: license-file
Dynamic: requires-dist
Dynamic: requires-python
Dynamic: summary
